<?xml version="1.0" encoding="utf-8"?>
<Dependencies>
  <Dependency>
    <ExtensionId>BinaryAnalysis.MultiLanguage</ExtensionId>
    <LoaderName>DynamicExtensionLoader</LoaderName>
    <VirtualPath>~/Modules/BinaryAnalysis.MultiLanguage/BinaryAnalysis.MultiLanguage.csproj</VirtualPath>
    <Hash>ca2049f73a5b4dde</Hash>
  </Dependency>
  <Dependency>
    <ExtensionId>Ipertrade.CultureLayer</ExtensionId>
    <LoaderName>DynamicExtensionLoader</LoaderName>
    <VirtualPath>~/Modules/Ipertrade.CultureLayer/Ipertrade.CultureLayer.csproj</VirtualPath>
    <Hash>97a9afcd670eef0b</Hash>
  </Dependency>
  <Dependency>
    <ExtensionId>Markdown</ExtensionId>
    <LoaderName>PrecompiledExtensionLoader</LoaderName>
    <VirtualPath>~/Modules/Markdown/bin/Markdown.dll</VirtualPath>
    <Hash>9238cf096098b57b</Hash>
  </Dependency>
  <Dependency>
    <ExtensionId>Mello.ImageGallery</ExtensionId>
    <LoaderName>DynamicExtensionLoader</LoaderName>
    <VirtualPath>~/Modules/Mello.ImageGallery/Mello.ImageGallery.csproj</VirtualPath>
    <Hash>5cfad274498b8f30</Hash>
  </Dependency>
  <Dependency>
    <ExtensionId>Orchard.Alias</ExtensionId>
    <LoaderName>PrecompiledExtensionLoader</LoaderName>
    <VirtualPath>~/Modules/Orchard.Alias/bin/Orchard.Alias.dll</VirtualPath>
    <Hash>48f79d1a8b30f620</Hash>
  </Dependency>
  <Dependency>
    <ExtensionId>Orchard.Autoroute</ExtensionId>
    <LoaderName>PrecompiledExtensionLoader</LoaderName>
    <VirtualPath>~/Modules/Orchard.Autoroute/bin/Orchard.Autoroute.dll</VirtualPath>
    <Hash>dba2980ba0b2c9e2</Hash>
  </Dependency>
  <Dependency>
    <ExtensionId>Orchard.Blogs</ExtensionId>
    <LoaderName>PrecompiledExtensionLoader</LoaderName>
    <VirtualPath>~/Modules/Orchard.Blogs/bin/Orchard.Blogs.dll</VirtualPath>
    <Hash>48f8051aed48152d</Hash>
  </Dependency>
  <Dependency>
    <ExtensionId>Orchard.Comments</ExtensionId>
    <LoaderName>PrecompiledExtensionLoader</LoaderName>
    <VirtualPath>~/Modules/Orchard.Comments/bin/Orchard.Comments.dll</VirtualPath>
    <Hash>92573f27c749ca49</Hash>
  </Dependency>
  <Dependency>
    <ExtensionId>Orchard.ContentTypes</ExtensionId>
    <LoaderName>PrecompiledExtensionLoader</LoaderName>
    <VirtualPath>~/Modules/Orchard.ContentTypes/bin/Orchard.ContentTypes.dll</VirtualPath>
    <Hash>4910cd33b72feb46</Hash>
  </Dependency>
  <Dependency>
    <ExtensionId>Orchard.CulturePicker</ExtensionId>
    <LoaderName>DynamicExtensionLoader</LoaderName>
    <VirtualPath>~/Modules/Orchard.CulturePicker/Orchard.CulturePicker.csproj</VirtualPath>
    <Hash>890be2e2e3a5a186</Hash>
  </Dependency>
  <Dependency>
    <ExtensionId>Orchard.Fields</ExtensionId>
    <LoaderName>PrecompiledExtensionLoader</LoaderName>
    <VirtualPath>~/Modules/Orchard.Fields/bin/Orchard.Fields.dll</VirtualPath>
    <Hash>48fb051df39df68d</Hash>
  </Dependency>
  <Dependency>
    <ExtensionId>Orchard.Forms</ExtensionId>
    <LoaderName>PrecompiledExtensionLoader</LoaderName>
    <VirtualPath>~/Modules/Orchard.Forms/bin/Orchard.Forms.dll</VirtualPath>
    <Hash>48f8851b70eb9c3d</Hash>
  </Dependency>
  <Dependency>
    <ExtensionId>Orchard.jQuery</ExtensionId>
    <LoaderName>PrecompiledExtensionLoader</LoaderName>
    <VirtualPath>~/Modules/Orchard.jQuery/bin/Orchard.jQuery.dll</VirtualPath>
    <Hash>48fc4d1f35d115b6</Hash>
  </Dependency>
  <Dependency>
    <ExtensionId>Orchard.Localization</ExtensionId>
    <LoaderName>DynamicExtensionLoader</LoaderName>
    <VirtualPath>~/Modules/Orchard.Localization/Orchard.Localization.csproj</VirtualPath>
    <Hash>fb91bcf4d801ed2b</Hash>
  </Dependency>
  <Dependency>
    <ExtensionId>Orchard.Media</ExtensionId>
    <LoaderName>PrecompiledExtensionLoader</LoaderName>
    <VirtualPath>~/Modules/Orchard.Media/bin/Orchard.Media.dll</VirtualPath>
    <Hash>92650f359a34f903</Hash>
  </Dependency>
  <Dependency>
    <ExtensionId>Orchard.MediaPicker</ExtensionId>
    <LoaderName>PrecompiledExtensionLoader</LoaderName>
    <VirtualPath>~/Modules/Orchard.MediaPicker/bin/Orchard.MediaPicker.dll</VirtualPath>
    <Hash>dbc48cb82504b724</Hash>
  </Dependency>
  <Dependency>
    <ExtensionId>Orchard.Modules</ExtensionId>
    <LoaderName>PrecompiledExtensionLoader</LoaderName>
    <VirtualPath>~/Modules/Orchard.Modules/bin/Orchard.Modules.dll</VirtualPath>
    <Hash>48ff1521f834350f</Hash>
  </Dependency>
  <Dependency>
    <ExtensionId>Orchard.Packaging</ExtensionId>
    <LoaderName>PrecompiledExtensionLoader</LoaderName>
    <VirtualPath>~/Modules/Orchard.Packaging/bin/Orchard.Packaging.dll</VirtualPath>
    <Hash>9257ca9db0a18a57</Hash>
  </Dependency>
  <Dependency>
    <ExtensionId>Orchard.Pages</ExtensionId>
    <LoaderName>PrecompiledExtensionLoader</LoaderName>
    <VirtualPath>~/Modules/Orchard.Pages/bin/Orchard.Pages.dll</VirtualPath>
    <Hash>48f7cd1ab7a36f26</Hash>
  </Dependency>
  <Dependency>
    <ExtensionId>Orchard.Projections</ExtensionId>
    <LoaderName>PrecompiledExtensionLoader</LoaderName>
    <VirtualPath>~/Modules/Orchard.Projections/bin/Orchard.Projections.dll</VirtualPath>
    <Hash>dba9c012c60443c7</Hash>
  </Dependency>
  <Dependency>
    <ExtensionId>Orchard.PublishLater</ExtensionId>
    <LoaderName>PrecompiledExtensionLoader</LoaderName>
    <VirtualPath>~/Modules/Orchard.PublishLater/bin/Orchard.PublishLater.dll</VirtualPath>
    <Hash>490fc532b2a27225</Hash>
  </Dependency>
  <Dependency>
    <ExtensionId>Orchard.Recipes</ExtensionId>
    <LoaderName>PrecompiledExtensionLoader</LoaderName>
    <VirtualPath>~/Modules/Orchard.Recipes/bin/Orchard.Recipes.dll</VirtualPath>
    <Hash>24fa6d8658d4600e</Hash>
  </Dependency>
  <Dependency>
    <ExtensionId>Orchard.Roles</ExtensionId>
    <LoaderName>PrecompiledExtensionLoader</LoaderName>
    <VirtualPath>~/Modules/Orchard.Roles/bin/Orchard.Roles.dll</VirtualPath>
    <Hash>48f8751b5891613b</Hash>
  </Dependency>
  <Dependency>
    <ExtensionId>Orchard.Rules</ExtensionId>
    <LoaderName>PrecompiledExtensionLoader</LoaderName>
    <VirtualPath>~/Modules/Orchard.Rules/bin/Orchard.Rules.dll</VirtualPath>
    <Hash>24efbd7bc41a96b8</Hash>
  </Dependency>
  <Dependency>
    <ExtensionId>Orchard.Scripting</ExtensionId>
    <LoaderName>PrecompiledExtensionLoader</LoaderName>
    <VirtualPath>~/Modules/Orchard.Scripting/bin/Orchard.Scripting.dll</VirtualPath>
    <Hash>4905e528ca3f62e9</Hash>
  </Dependency>
  <Dependency>
    <ExtensionId>Orchard.Setup</ExtensionId>
    <LoaderName>PrecompiledExtensionLoader</LoaderName>
    <VirtualPath>~/Modules/Orchard.Setup/bin/Orchard.Setup.dll</VirtualPath>
    <Hash>6e4782f672300de2</Hash>
  </Dependency>
  <Dependency>
    <ExtensionId>Orchard.Tags</ExtensionId>
    <LoaderName>PrecompiledExtensionLoader</LoaderName>
    <VirtualPath>~/Modules/Orchard.Tags/bin/Orchard.Tags.dll</VirtualPath>
    <Hash>48f4c517a94c8dc5</Hash>
  </Dependency>
  <Dependency>
    <ExtensionId>Orchard.Themes</ExtensionId>
    <LoaderName>PrecompiledExtensionLoader</LoaderName>
    <VirtualPath>~/Modules/Orchard.Themes/bin/Orchard.Themes.dll</VirtualPath>
    <Hash>48fb7d1e5fc1349c</Hash>
  </Dependency>
  <Dependency>
    <ExtensionId>Orchard.Tokens</ExtensionId>
    <LoaderName>PrecompiledExtensionLoader</LoaderName>
    <VirtualPath>~/Modules/Orchard.Tokens/bin/Orchard.Tokens.dll</VirtualPath>
    <Hash>48fbed1ed9589caa</Hash>
  </Dependency>
  <Dependency>
    <ExtensionId>Orchard.Users</ExtensionId>
    <LoaderName>PrecompiledExtensionLoader</LoaderName>
    <VirtualPath>~/Modules/Orchard.Users/bin/Orchard.Users.dll</VirtualPath>
    <Hash>48f8dd1bbbd9ad48</Hash>
  </Dependency>
  <Dependency>
    <ExtensionId>Orchard.Warmup</ExtensionId>
    <LoaderName>PrecompiledExtensionLoader</LoaderName>
    <VirtualPath>~/Modules/Orchard.Warmup/bin/Orchard.Warmup.dll</VirtualPath>
    <Hash>48fc2d1f12398eb2</Hash>
  </Dependency>
  <Dependency>
    <ExtensionId>Orchard.Widgets</ExtensionId>
    <LoaderName>PrecompiledExtensionLoader</LoaderName>
    <VirtualPath>~/Modules/Orchard.Widgets/bin/Orchard.Widgets.dll</VirtualPath>
    <Hash>dba8e811d4e092ac</Hash>
  </Dependency>
  <Dependency>
    <ExtensionId>TinyMce</ExtensionId>
    <LoaderName>PrecompiledExtensionLoader</LoaderName>
    <VirtualPath>~/Modules/TinyMce/bin/TinyMce.dll</VirtualPath>
    <Hash>48e68d09731912fe</Hash>
  </Dependency>
  <Dependency>
    <ExtensionId>UpgradeTo14</ExtensionId>
    <LoaderName>PrecompiledExtensionLoader</LoaderName>
    <VirtualPath>~/Modules/UpgradeTo14/bin/UpgradeTo14.dll</VirtualPath>
    <Hash>24e71d7333b70ba4</Hash>
  </Dependency>
</Dependencies>